feature_selection/__init__.py
feature_selection/base.py
feature_selection/binary_black_hole.py
feature_selection/genetic_algorithm.py
feature_selection/harmonic_search.py
feature_selection/metaheuristics.py
feature_selection/random_search.py
feature_selection/simulated_anneling.py
feature_selection/tests/__init__.py
feature_selection/tests/check_test.py
feature_selection/tests/just_kiiding.py
feature_selection/tests/plot_ga_hs.py
feature_selection/tests/utils.py
metaheuristic-1.3.dist-info/DESCRIPTION.rst
metaheuristic-1.3.dist-info/METADATA
metaheuristic-1.3.dist-info/RECORD
metaheuristic-1.3.dist-info/WHEEL
metaheuristic-1.3.dist-info/metadata.json
metaheuristic-1.3.dist-info/top_level.txt
