Metadata-Version: 2.0
Name: metaheuristic
Version: 1.3
Summary: A package with some metaheuristics to feature selection
Home-page: https://github.com/gonzalesMK/MetaHeuristic
Author: Juliano D. Negri
Author-email: julianonegri@gmail.com
License: UNKNOWN
Platform: UNKNOWN
Classifier: Programming Language :: Python :: 3.6
Classifier: Development Status :: 3 - Alpha
Classifier: Intended Audience :: Science/Research
Classifier: Topic :: Scientific/Engineering :: Information Analysis
Classifier: Topic :: Software Development :: Libraries
Requires-Dist: DEAP (>=1.0)
Requires-Dist: matplotlib (>=1.5.2,<=2.0.2)
Requires-Dist: nose (>=1.1.2)
Requires-Dist: numpydoc (>=0.5)
Requires-Dist: scikit-learn (>=0.17)
Requires-Dist: scipy (>=0.19)
Requires-Dist: sphinx-gallery (>=0.1.11)
